opencarp_analyzer/__init__.py
opencarp_analyzer/analyzer.py
opencarp_analyzer/plotter.py
opencarp_analyzer/version.json
opencarp_analyzer-1.0.7.data/data/opencarp_analyzer/version.json
opencarp_analyzer-1.0.7.dist-info/METADATA
opencarp_analyzer-1.0.7.dist-info/WHEEL
opencarp_analyzer-1.0.7.dist-info/entry_points.txt
opencarp_analyzer-1.0.7.dist-info/top_level.txt
opencarp_analyzer-1.0.7.dist-info/RECORD
