Metadata-Version: 2.1
Name: opencarp-analyzer
Version: 1.0.7
Summary: OpenCARP Trace Analyzer
Home-page: https://github.com/regmibijay/opencarp-analyzer
Author: Bijay Regmi
Author-email: opencarp-analyzer@regdelivery.de
License: MIT
Platform: UNKNOWN
Classifier: Programming Language :: Python :: 3
Classifier: License :: OSI Approved :: MIT License
Classifier: Operating System :: OS Independent
Requires-Python: >=3.6
Requires-Dist: matplotlib
Requires-Dist: pandas
